asyncwebsockets/__init__.py
asyncwebsockets/client.py
asyncwebsockets/server.py
asyncwebsockets/websocket.py
asyncwebsockets-0.9.4.dist-info/LICENCE
asyncwebsockets-0.9.4.dist-info/METADATA
asyncwebsockets-0.9.4.dist-info/WHEEL
asyncwebsockets-0.9.4.dist-info/top_level.txt
asyncwebsockets-0.9.4.dist-info/RECORD
