Metadata-Version: 2.1
Name: asyncwebsockets
Version: 0.9.4
Summary: A websocket library
Home-page: https://github.com/Fuyukai/asyncwebsockets
Author: Laura Dickinson
Author-email: l@veriny.tf
License: MIT
Classifier: Intended Audience :: Developers
Classifier: Programming Language :: Python :: 3
Classifier: Framework :: AsyncIO
Classifier: Framework :: Trio
Classifier: Intended Audience :: Developers
Classifier: License :: OSI Approved
Classifier: Topic :: Internet :: WWW/HTTP
Requires-Python: >=3.6
License-File: LICENCE
